codeinspector/__init__.py
codeinspector/agents.py
codeinspector/cli.py
codeinspector/config.py
codeinspector/git_handler.py
codeinspector/github_client.py
codeinspector/quality_checker.py
codeinspector/adk/__init__.py
codeinspector/adk/agent.py
codeinspector/auth/__init__.py
codeinspector/auth/login.py
codeinspector/commands/__init__.py
codeinspector/commands/config.py
codeinspector/commands/rules.py
codeinspector/data/__init__.py
codeinspector/data/adapters.py
codeinspector/db/__init__.py
codeinspector/db/pr_repository.py
codeinspector/db/repository.py
codeinspector/db/schema.py
codeinspector/github/__init__.py
codeinspector/github/pr_reviewer.py
codeinspector/jobs/__init__.py
codeinspector/jobs/job_runner.py
codeinspector/llm/__init__.py
codeinspector/llm/gemini_client.py
codeinspector/mcp_toolbox/__init__.py
codeinspector/mcp_toolbox/toolbox.py
codeinspector-0.1.2.dist-info/METADATA
codeinspector-0.1.2.dist-info/WHEEL
codeinspector-0.1.2.dist-info/entry_points.txt
codeinspector-0.1.2.dist-info/top_level.txt
codeinspector-0.1.2.dist-info/RECORD
