Metadata-Version: 2.4
Name: codeinspector
Version: 0.1.2
Summary: An AI-powered Senior Engineer Agent for your terminal.
Home-page: https://github.com/pranaykesava/code-inspector-ai
Author: Pranay & Gnanesh
Author-email: pranaykesava@gmail.com
Classifier: Programming Language :: Python :: 3
Classifier: License :: OSI Approved :: MIT License
Classifier: Operating System :: OS Independent
Requires-Python: >=3.8
Requires-Dist: click
Requires-Dist: gitpython
Requires-Dist: pygithub
Requires-Dist: google-generativeai
Requires-Dist: flake8
Requires-Dist: pytest
Requires-Dist: coverage
Requires-Dist: PyYAML
Dynamic: author
Dynamic: author-email
Dynamic: classifier
Dynamic: description
Dynamic: description-content-type
Dynamic: home-page
Dynamic: requires-dist
Dynamic: requires-python
Dynamic: summary
